_plotly_future_/__init__.py
_plotly_future_/extract_chart_studio.py
_plotly_future_/orca_defaults.py
_plotly_future_/remove_deprecations.py
_plotly_future_/renderer_defaults.py
_plotly_future_/template_defaults.py
_plotly_future_/timezones.py
_plotly_future_/trace_uids.py
_plotly_future_/v4.py
_plotly_future_/v4_subplots.py
_plotly_utils/__init__.py
_plotly_utils/basevalidators.py
_plotly_utils/exceptions.py
_plotly_utils/files.py
_plotly_utils/optional_imports.py
_plotly_utils/utils.py
_plotly_utils/colors/__init__.py
_plotly_utils/colors/_swatches.py
_plotly_utils/colors/carto.py
_plotly_utils/colors/cmocean.py
_plotly_utils/colors/colorbrewer.py
_plotly_utils/colors/cyclical.py
_plotly_utils/colors/diverging.py
_plotly_utils/colors/plotlyjs.py
_plotly_utils/colors/qualitative.py
_plotly_utils/colors/sequential.py
plotly/__init__.py
plotly/_docstring_gen.py
plotly/_version.py
plotly/_widget_version.py
plotly/animation.py
plotly/basedatatypes.py
plotly/basewidget.py
plotly/callbacks.py
plotly/colors.py
plotly/config.py
plotly/conftest.py
plotly/dashboard_objs.py
plotly/exceptions.py
plotly/files.py
plotly/graph_objects.py
plotly/grid_objs.py
plotly/optional_imports.py
plotly/presentation_objs.py
plotly/serializers.py
plotly/session.py
plotly/subplots.py
plotly/tools.py
plotly/utils.py
plotly/version.py
plotly/widgets.py
plotly/data/__init__.py
plotly/express/__init__.py
plotly/express/_chart_types.py
plotly/express/_core.py
plotly/express/_doc.py
plotly/express/_imshow.py
plotly/express/colors.py
plotly/express/data.py
plotly/figure_factory/_2d_density.py
plotly/figure_factory/__init__.py
plotly/figure_factory/_annotated_heatmap.py
plotly/figure_factory/_bullet.py
plotly/figure_factory/_candlestick.py
plotly/figure_factory/_county_choropleth.py
plotly/figure_factory/_dendrogram.py
plotly/figure_factory/_distplot.py
plotly/figure_factory/_facet_grid.py
plotly/figure_factory/_gantt.py
plotly/figure_factory/_ohlc.py
plotly/figure_factory/_quiver.py
plotly-4.5.4.dist-info/LICENSE.txt
plotly-4.5.4.dist-info/METADATA
plotly-4.5.4.dist-info/WHEEL
plotly-4.5.4.dist-info/top_level.txt
plotly-4.5.4.dist-info/RECORD
