Metadata-Version: 2.1
Name: plotly
Version: 4.5.4
Summary: An open-source, interactive graphing library for Python
Home-page: https://plot.ly/python/
Author: Chris P
Author-email: chris@plot.ly
Maintainer: Jon Mease
Maintainer-email: jon@plot.ly
License: MIT
Project-URL: Github, https://github.com/plotly/plotly.py
Platform: UNKNOWN
Classifier: Development Status :: 5 - Production/Stable
Classifier: Programming Language :: Python :: 2
Classifier: Programming Language :: Python :: 2.7
Classifier: Programming Language :: Python :: 3
Classifier: Programming Language :: Python :: 3.3
Classifier: Programming Language :: Python :: 3.4
Classifier: Programming Language :: Python :: 3.5
Classifier: Programming Language :: Python :: 3.6
Classifier: Programming Language :: Python :: 3.7
Classifier: Topic :: Scientific/Engineering :: Visualization
